aliyunsdkactiontrail/__init__.py
aliyunsdkactiontrail/endpoint.py
aliyunsdkactiontrail/request/__init__.py
aliyunsdkactiontrail/request/v20200706/CreateDeliveryHistoryJobRequest.py
aliyunsdkactiontrail/request/v20200706/CreateTrailRequest.py
aliyunsdkactiontrail/request/v20200706/DeleteDeliveryHistoryJobRequest.py
aliyunsdkactiontrail/request/v20200706/DeleteTrailRequest.py
aliyunsdkactiontrail/request/v20200706/DescribeRegionsRequest.py
aliyunsdkactiontrail/request/v20200706/DescribeTrailsRequest.py
aliyunsdkactiontrail/request/v20200706/GetAccessKeyLastUsedEventsRequest.py
aliyunsdkactiontrail/request/v20200706/GetAccessKeyLastUsedInfoRequest.py
aliyunsdkactiontrail/request/v20200706/GetAccessKeyLastUsedIpsRequest.py
aliyunsdkactiontrail/request/v20200706/GetAccessKeyLastUsedProductsRequest.py
aliyunsdkactiontrail/request/v20200706/GetAccessKeyLastUsedResourcesRequest.py
aliyunsdkactiontrail/request/v20200706/GetDeliveryHistoryJobRequest.py
aliyunsdkactiontrail/request/v20200706/GetTrailStatusRequest.py
aliyunsdkactiontrail/request/v20200706/ListDeliveryHistoryJobsRequest.py
aliyunsdkactiontrail/request/v20200706/LookupEventsRequest.py
aliyunsdkactiontrail/request/v20200706/StartLoggingRequest.py
aliyunsdkactiontrail/request/v20200706/StopLoggingRequest.py
aliyunsdkactiontrail/request/v20200706/UpdateTrailRequest.py
aliyunsdkactiontrail/request/v20200706/__init__.py
aliyun_python_sdk_actiontrail-2.2.0.dist-info/LICENSE
aliyun_python_sdk_actiontrail-2.2.0.dist-info/METADATA
aliyun_python_sdk_actiontrail-2.2.0.dist-info/WHEEL
aliyun_python_sdk_actiontrail-2.2.0.dist-info/top_level.txt
aliyun_python_sdk_actiontrail-2.2.0.dist-info/RECORD
